urbandictionary.py
urbandictionary_fixed-2.0.dist-info/LICENSE
urbandictionary_fixed-2.0.dist-info/METADATA
urbandictionary_fixed-2.0.dist-info/WHEEL
urbandictionary_fixed-2.0.dist-info/top_level.txt
urbandictionary_fixed-2.0.dist-info/RECORD
